Digital Systems - Lab/Experiment 11/dec_3to8.v
`timescale 1ns / 1ps
//////////////////////////////////////////////////////////////////////////////////
// Company: 
// Engineer: 
// 
// Create Date:    15:33:39 04/01/2019 
// Design Name: 
// Module Name:    dec_3to8 
// Project Name: 
// Target Devices: 
// Tool versions: 
// Description: 
//
// Dependencies: 
//
// Revision: 
// Revision 0.01 - File Created
// Additional Comments: 
//
//////////////////////////////////////////////////////////////////////////////////
module dec_3to8(a, l);

	input [2:0] a;
	output reg [7:0] l;
	

	always@(a)
	begin
	
		case(a)
		
			3'b000 : l = 8'b00000001;
			3'b001 : l = 8'b00000010;
			3'b010 : l = 8'b00000100;
			3'b011 : l = 8'b00001000;
			3'b100 : l = 8'b00010000;
			3'b101 : l = 8'b00100000;
			3'b110 : l = 8'b01000000;
			3'b111 : l = 8'b10000000;
		
			default : l = 8'b00000000;
		
		endcase
	
	end
	
endmodule

Digital Systems - Lab/Experiment 11/dec_3to8_tb.v
`timescale 1ns / 1ps

////////////////////////////////////////////////////////////////////////////////
// Company: 
// Engineer:
//
// Create Date:   15:41:33 04/01/2019
// Design Name:   dec_3to8
// Module Name:   C:/Users/students/Desktop/PSM/dec_3to8/test_3to8.v
// Project Name:  dec_3to8
// Target Device:  
// Tool versions:  
// Description: 
//
// Verilog Test Fixture created by ISE for module: dec_3to8
//
// Dependencies:
// 
// Revision:
// Revision 0.01 - File Created
// Additional Comments:
// 
////////////////////////////////////////////////////////////////////////////////

module test_3to8;

	// Inputs
	reg [2:0] a;

	// Outputs
	wire [7:0] l;

	// Instantiate the Unit Under Test (UUT)
	dec_3to8 uut (.a(a), .l(l));

	initial 
	begin
		// Initialize Inputs
		a = 0;

		// Wait 100 ns for global reset to finish
		#100
			a = 3'b001;
		#100
			a = 3'b010;
		#100
			a = 3'b011;
        #100
        	a = 3'b100;
        #100
			a = 3'b101;
		#100
			a = 3'b110;
        #100
        	a = 3'b111;
         
	end

	initial
	begin
		$dumpfile("dec_3-8.vcd");
		$dumpvars(0,test_3to8);
	end
      
endmodule

Digital Systems - Lab/Experiment 11/dec_3-8.vcd
$date
	Tue Apr  2 17:35:40 2019
$end
$version
	Icarus Verilog
$end
$timescale
	1ps
$end
$scope module test_3to8 $end
$var wire 8 ! l [7:0] $end
$var reg 3 " a [2:0] $end
$scope module uut $end
$var wire 3 # a [2:0] $end
$var reg 8 $ l [7:0] $end
$upscope $end
$upscope $end
$enddefinitions $end
#0
$dumpvars
b1 $
b0 #
b0 "
b1 !
$end
#100000
b10 !
b10 $
b1 "
b1 #
#200000
b100 !
b100 $
b10 "
b10 #
#300000
b1000 !
b1000 $
b11 "
b11 #
#400000
b10000 !
b10000 $
b100 "
b100 #
#500000
b100000 !
b100000 $
b101 "
b101 #
#600000
b1000000 !
b1000000 $
b110 "
b110 #
#700000
b10000000 !
b10000000 $
b111 "
b111 #
