Digital Systems - Lab/Experiment 11/multiplier_2bit.v
`timescale 1ns/1ps

module multiplier_2bit(a, b, o);

        input [1:0] a;
        input [1:0] b;
        output [3:0] o;

        wire t1a, t1b, t2a, t2b;

        and a0(o[0], a[0], b[0]);

        and a1a(t1a, a[1], b[0]);
        and a1b(t1b, a[0], b[1]);
        xor x1(o[1], t1a, t1b);

        and a2a(t2a, a[0], a[1], b[0], b[1]);
        and a2b(t2b, a[1], b[1]);
        xor x2(o[2], t2a, t2b);

        assign o[3] = t2a;


endmodule

Digital Systems - Lab/Experiment 11/multiplier_2bit_tb.v
`timescale 1ns / 1ps

////////////////////////////////////////////////////////////////////////////////
// Company: 
// Engineer:
//
// Create Date:   15:41:37 04/02/2019
// Design Name:   multiplier_2bit
// Module Name:   C:/Users/students/Desktop/PSM/exp11/multiplier_2bit/mul_tb.v
// Project Name:  multiplier_2bit
// Target Device:  
// Tool versions:  
// Description: 
//
// Verilog Test Fixture created by ISE for module: multiplier_2bit
//
// Dependencies:
// 
// Revision:
// Revision 0.01 - File Created
// Additional Comments:
// 
////////////////////////////////////////////////////////////////////////////////


module testbench_mult;

        initial 
        begin
                $dumpfile("mult_2bit.vcd");
                $dumpvars(0, testbench_mult);
        end

        wire[3:0] out;
        reg[1:0] i1, i2;

        multiplier_2bit m(i1, i2, out);

        initial
        begin

                i1=2'b00; i2=2'b00;
            #10 i1=2'b01; i2=2'b00;
            #10 i1=2'b10; i2=2'b00;
            #10 i1=2'b11; i2=2'b00;
            #10 i1=2'b00; i2=2'b01;
            #10 i1=2'b01; i2=2'b01;
            #10 i1=2'b10; i2=2'b01;
            #10 i1=2'b11; i2=2'b01;
            #10 i1=2'b00; i2=2'b10;
            #10 i1=2'b01; i2=2'b10;
            #10 i1=2'b10; i2=2'b10;
            #10 i1=2'b11; i2=2'b10;
            #10 i1=2'b00; i2=2'b11;
            #10 i1=2'b01; i2=2'b11;
            #10 i1=2'b10; i2=2'b11;
            #10 i1=2'b11; i2=2'b11;

            #10 $finish;
        end

endmodule

Digital Systems - Lab/Experiment 11/mult_2bit.vcd
$date
	Tue Apr  2 17:36:51 2019
$end
$version
	Icarus Verilog
$end
$timescale
	1ps
$end
$scope module testbench_mult $end
$var wire 4 ! out [3:0] $end
$var reg 2 " i1 [1:0] $end
$var reg 2 # i2 [1:0] $end
$scope module m $end
$var wire 2 $ a [1:0] $end
$var wire 2 % b [1:0] $end
$var wire 1 & t1a $end
$var wire 1 ' t1b $end
$var wire 1 ( t2a $end
$var wire 1 ) t2b $end
$var wire 4 * o [3:0] $end
$upscope $end
$upscope $end
$enddefinitions $end
#0
$dumpvars
b0 *
0)
0(
0'
0&
b0 %
b0 $
b0 #
b0 "
b0 !
$end
#10000
b1 "
b1 $
#20000
b10 "
b10 $
#30000
b11 "
b11 $
#40000
b1 #
b1 %
b0 "
b0 $
#50000
b1 !
b1 *
b1 "
b1 $
#60000
b10 !
b10 *
1&
b10 "
b10 $
#70000
b11 !
b11 *
b11 "
b11 $
#80000
b0 !
b0 *
0&
b10 #
b10 %
b0 "
b0 $
#90000
b10 !
b10 *
1'
b1 "
b1 $
#100000
b100 !
b100 *
0'
1)
b10 "
b10 $
#110000
b110 !
b110 *
1'
b11 "
b11 $
#120000
b0 !
b0 *
0'
0)
b11 #
b11 %
b0 "
b0 $
#130000
b11 !
b11 *
1'
b1 "
b1 $
#140000
b110 !
b110 *
1&
0'
1)
b10 "
b10 $
#150000
1'
b1001 !
b1001 *
1(
b11 "
b11 $
